src/rtl/register_file.v
module register_file #(
    parameter integer DATA_WIDTH = 8,
    parameter integer ADDR_WIDTH = 3,
    parameter integer NUM_REG = 2 ** ADDR_WIDTH
)(
    input wire [ADDR_WIDTH-1:0] WRITE_ADDR,
    input wire [ADDR_WIDTH-1:0] READ_ADDR1,
    input wire [ADDR_WIDTH-1:0] READ_ADDR2,
    input wire CLK,
    input wire WRITE_EN,
    input wire RST_N,
    input wire [DATA_WIDTH-1:0] WRITE_DATA,

    output reg [DATA_WIDTH-1:0] READ_DATA1,
    output reg [DATA_WIDTH-1:0] READ_DATA2

);

reg [DATA_WIDTH-1:0] register [0:NUM_REG-1];
wire [NUM_REG-1:0] one_hot;
integer i;
integer k;
assign one_hot = (1 << WRITE_ADDR);

always @(posedge CLK or negedge RST_N) begin
    if(!RST_N) begin
        for(k=0;k<NUM_REG;k=k+1) begin
            register[k] <= {DATA_WIDTH{1'b0}};
        end
    end
    else begin
        register[0] <= 0;
        if(WRITE_EN && WRITE_ADDR != 0) begin
            for(i=0;i<NUM_REG;i=i+1) begin
                if (one_hot[i] == 1'b1) begin
                    register[i] <= WRITE_DATA;
                end
            end
        end
    end
    if(WRITE_EN && (WRITE_ADDR == READ_ADDR1)) begin
        READ_DATA1 <= WRITE_DATA;
    end else begin
        READ_DATA1 <= register[READ_ADDR1];
    end
    if(WRITE_EN && (WRITE_ADDR == READ_ADDR2)) begin
        READ_DATA2 <= WRITE_DATA;
    end else begin
        READ_DATA2 <= register[READ_ADDR2];
    end

end
endmodule

src/tb/register_file_tb.v
`timescale 1ns/1ps

module register_file_tb;
parameter DATA_WIDTH = 8;
parameter ADDR_WIDTH = 3;

reg [ADDR_WIDTH-1:0] WRITE_ADDR;
reg [ADDR_WIDTH-1:0] READ_ADDR1;
reg [ADDR_WIDTH-1:0] READ_ADDR2;
reg CLK;
reg WRITE_EN;
reg RST_N;
reg [DATA_WIDTH-1:0] WRITE_DATA;

wire [DATA_WIDTH-1:0] READ_DATA1;
wire [DATA_WIDTH-1:0] READ_DATA2;

register_file#(
    .DATA_WIDTH(DATA_WIDTH),
    .ADDR_WIDTH(ADDR_WIDTH)
)dut(
    .WRITE_ADDR(WRITE_ADDR),
    .READ_ADDR1(READ_ADDR1),
    .READ_ADDR2(READ_ADDR2),
    .CLK(CLK),
    .WRITE_EN(WRITE_EN),
    .RST_N(RST_N),
    .WRITE_DATA(WRITE_DATA),
    .READ_DATA1(READ_DATA1),
    .READ_DATA2(READ_DATA2)
);

initial CLK = 0;
always #5 CLK = ~CLK;
initial begin
    $dumpfile("waveform/register_file_op.vcd");
    $dumpvars(0,register_file_tb);
    #10
    RST_N = 0;
    READ_ADDR1 = 0;
    READ_ADDR2 = 0;
    WRITE_DATA = 0;
    WRITE_EN = 0;
    WRITE_ADDR = 0;

    #10
    RST_N = 1;
    #10
    WRITE_ADDR = 4'h1;
    WRITE_DATA = 8'hFF;
    WRITE_EN = 0;

    #10
    WRITE_EN = 1;

    #10
    WRITE_ADDR = 4'h2;
    WRITE_DATA = 8'hFE;

    #10
    WRITE_EN = 0;

    #10
    READ_ADDR1 = 4'h1;
    READ_ADDR2 = 4'h2;

    #10
    WRITE_ADDR = 4'h0;
    WRITE_DATA = 8'hFE;

    #10
    WRITE_ADDR = 4'h0;
    WRITE_DATA = 8'hAA;
    WRITE_EN = 1;

    #100
    $finish;
end

endmodule

src/waveform/register_file_op.vcd
$date
	Thu Mar 26 23:35:18 2026
$end
$version
	Icarus Verilog
$end
$timescale
	1ps
$end
$scope module register_file_tb $end
$var wire 8 ! READ_DATA2 [7:0] $end
$var wire 8 " READ_DATA1 [7:0] $end
$var parameter 32 # ADDR_WIDTH $end
$var parameter 32 $ DATA_WIDTH $end
$var reg 1 % CLK $end
$var reg 3 & READ_ADDR1 [2:0] $end
$var reg 3 ' READ_ADDR2 [2:0] $end
$var reg 1 ( RST_N $end
$var reg 3 ) WRITE_ADDR [2:0] $end
$var reg 8 * WRITE_DATA [7:0] $end
$var reg 1 + WRITE_EN $end
$scope module dut $end
$var wire 1 % CLK $end
$var wire 3 , READ_ADDR1 [2:0] $end
$var wire 3 - READ_ADDR2 [2:0] $end
$var wire 1 ( RST_N $end
$var wire 3 . WRITE_ADDR [2:0] $end
$var wire 8 / WRITE_DATA [7:0] $end
$var wire 1 + WRITE_EN $end
$var wire 8 0 one_hot [7:0] $end
$var parameter 32 1 ADDR_WIDTH $end
$var parameter 32 2 DATA_WIDTH $end
$var parameter 32 3 NUM_REG $end
$var reg 8 4 READ_DATA1 [7:0] $end
$var reg 8 5 READ_DATA2 [7:0] $end
$var integer 32 6 i [31:0] $end
$var integer 32 7 k [31:0] $end
$upscope $end
$upscope $end
$enddefinitions $end
$comment Show the parameter values. $end
$dumpall
b1000 3
b1000 2
b11 1
b1000 $
b11 #
$end
#0
$dumpvars
bx 7
bx 6
bx 5
bx 4
bx 0
bx /
bx .
bx -
bx ,
x+
bx *
bx )
x(
bx '
bx &
0%
bx "
bx !
$end
#5000
1%
#10000
b0 !
b0 5
b0 "
b0 4
b1000 7
0%
b1 0
b0 )
b0 .
0+
b0 *
b0 /
b0 '
b0 -
b0 &
b0 ,
0(
#15000
b1000 7
1%
#20000
0%
1(
#25000
1%
#30000
0%
b11111111 *
b11111111 /
b10 0
b1 )
b1 .
#35000
1%
#40000
0%
1+
#45000
b1000 6
1%
#50000
0%
b11111110 *
b11111110 /
b100 0
b10 )
b10 .
#55000
b1000 6
1%
#60000
0%
0+
#65000
1%
#70000
0%
b10 '
b10 -
b1 &
b1 ,
#75000
b11111110 !
b11111110 5
b11111111 "
b11111111 4
1%
#80000
0%
b1 0
b0 )
b0 .
#85000
1%
#90000
0%
1+
b10101010 *
b10101010 /
